{"name":"sSMS","tagline":"electronic School Management System","body":"eSMS\r\n====\r\n\r\nelectronic School Management System\r\n\r\neSMS (electronic School Management System) \r\n electronic School Management System helps schools in managing student's data. It is targeted for colleges in the Philippines.\r\n It is developed in C#/VB.Net and uses MySQL as the database.\r\n\r\nThe system is divided into several modules:\r\n\r\n1. Registrar Module - used by the Registrar.\r\n2. Scheduling Module - used by Deans for creating course offerings schedule\r\n3. Cashiering Module - used by the Accounting Department\r\n4. Grading Entry Module - used by teachers for encoding grades.\r\n5. Advising Module - used by the different departments for advising students. \r\n6. Admission Module - used by the Department of Student Affairs (DSA).\r\n7. Administration Module - used by the system administrator for controlling the behavior of the system.\r\n","google":"","note":"Don't delete this file! It's used internally to help with page regeneration."}